{"project_info":{"project_id":"androidmapproject-1111","project_number":"260506023716","name":"AndroidMapProject"},"client":[{"client_info":{"mobilesdk_app_id":"1:260506023716:android:42c7865050ea61ba","client_id":"android:com.vibeosys.travelapp","client_type":1,"android_client_info":{"package_name":"com.vibeosys.travelapp"}},"oauth_client":[{"client_id":"260506023716-pumuu3t383o673v7tvo73eah3ljhenb3.apps.googleusercontent.com","client_type":1,"android_info":{"package_name":"com.vibeosys.travelapp","certificate_hash":"c1c0527eb56c4579ace44d7efb4ff059c83f0df1"}}],"api_key":[],"services":{"analytics_service":{"status":1},"cloud_messaging_service":{"status":1,"apns_config":[]},"appinvite_service":{"status":1,"other_platform_oauth_client":[]},"google_signin_service":{"status":2},"ads_service":{"status":1}}}],"client_info":[],"ARTIFACT_VERSION":"1"}